gtranstomp3/__init__.py
gtranstomp3/logger.py
gtranstomp3/main.py
gtranstomp3/utils.py
gtranstomp3/pipeline/__init__.py
gtranstomp3/pipeline/pipeline.py
gtranstomp3/pipeline/steps/__init__.py
gtranstomp3/pipeline/steps/get_sentence.py
gtranstomp3/pipeline/steps/get_user_input.py
gtranstomp3/pipeline/steps/read_files.py
gtranstomp3/pipeline/steps/step.py
gtranstomp3/pipeline/steps/translate_to_mp3.py
gtranstomp3-0.1.1.dist-info/LICENSE
gtranstomp3-0.1.1.dist-info/METADATA
gtranstomp3-0.1.1.dist-info/WHEEL
gtranstomp3-0.1.1.dist-info/top_level.txt
gtranstomp3-0.1.1.dist-info/RECORD
