Metadata-Version: 2.1
Name: gtranstomp3
Version: 0.1.1
Summary: Create a mp3 file include English words and translated Traditional Chinese and its example sentenses.
Home-page: https://github.com/PoHandsome/gtranstomp3
Author: Po-Han Chen
Author-email: louisfat54108@gmail.com
License: MIT
Platform: UNKNOWN
Classifier: License :: OSI Approved :: MIT License
Classifier: Programming Language :: Python
Classifier: Programming Language :: Python :: 3
Classifier: Programming Language :: Python :: 3.6
Classifier: Programming Language :: Python :: Implementation :: CPython
Classifier: Programming Language :: Python :: Implementation :: PyPy
Requires-Python: >=3.6.0
License-File: LICENSE
Requires-Dist: googletrans (==4.0.0rc1)
Requires-Dist: selenium
Requires-Dist: gtts
Provides-Extra: test_use
Requires-Dist: pytest ; extra == 'test_use'
